testlmro/__init__.py
testlmro/m_mod_lmro.py
testlmroczkowski-0.0.1.dist-info/LICENSE.txt
testlmroczkowski-0.0.1.dist-info/METADATA
testlmroczkowski-0.0.1.dist-info/WHEEL
testlmroczkowski-0.0.1.dist-info/top_level.txt
testlmroczkowski-0.0.1.dist-info/RECORD
