Metadata-Version: 2.1
Name: testlmroczkowski
Version: 0.0.1
Summary: My test package
Author-email: Lukasz <lmrocsk@gmai.com>
License: MIT License
Keywords: test,testlmroczkowski,name,surname,first_package
Classifier: Framework :: IDLE
Classifier: Natural Language :: Polish
Requires-Python: >=3.0
License-File: LICENSE.txt
Requires-Dist: python-version (>='3.0')
Requires-Dist: numpy
